catadoc/__init__.py
catadoc/__main__.py
catadoc/feed.py
catadoc/viewer.py
catadoc-1.1.1.dist-info/LICENSE
catadoc-1.1.1.dist-info/METADATA
catadoc-1.1.1.dist-info/WHEEL
catadoc-1.1.1.dist-info/entry_points.txt
catadoc-1.1.1.dist-info/top_level.txt
catadoc-1.1.1.dist-info/RECORD
